mathpackage.py
mathpackage-0.0.2.dist-info/METADATA
mathpackage-0.0.2.dist-info/WHEEL
mathpackage-0.0.2.dist-info/top_level.txt
mathpackage-0.0.2.dist-info/RECORD
