Metadata-Version: 2.1
Name: mathpackage
Version: 0.0.2
Summary: Math Tools
Home-page: UNKNOWN
Author: Manlow Charumbira
License: UNKNOWN
Platform: UNKNOWN
Classifier: Programming Language :: Python :: 3
Classifier: License :: OSI Approved :: MIT License
Classifier: Operating System :: OS Independent
Requires-Python: >=3.6
